dead_resources.py
setup.py
simplescrape.egg-info/PKG-INFO
simplescrape.egg-info/SOURCES.txt
simplescrape.egg-info/dependency_links.txt
simplescrape.egg-info/requires.txt
simplescrape.egg-info/top_level.txt