Metadata-Version: 1.0
Name: simplescrape
Version: 0.0.1
Summary: simple dead resource finder
Home-page: https://github.com/rranshous/simplescrape
Author: Robby Ranshous
Author-email: rranshous@gmail.com
License: UNKNOWN
Keywords: scraping
Platform: UNKNOWN
Classifier: Development Status :: 3 - Alpha
Classifier: Topic :: Utilities
Classifier: Programming Language :: Python :: 2.6
Classifier: Programming Language :: Python :: 2.7
